[
  {
    "id": "88cb96b4-0ffe-4056-ab51-4c4c2115d34d",
    "name": "Universit\u00e4tsklinikum Hamburg-Eppendorf (UKE)",
    "department": "Cardiology",
    "title": "Research Assistant in Cardiology",
    "description": "Support ongoing research in heart failure studies",
    "duration": "3 months",
    "requirements": [
      "Basic ECG knowledge",
      "Medical student year 2+"
    ],
    "location": "Martinistra\u00dfe 52, 20251 Hamburg",
    "latitude": 53.5897,
    "longitude": 9.9756,
    "stipend": 750.0,
    "created_at": "2025-04-17T13:48:44.392357",
    "updated_at": "2025-04-17T13:48:44.392364"
  },
  {
    "id": "1af32d78-d785-4e4b-9bb3-7444734ef3b0",
    "name": "Asklepios Klinik St. Georg",
    "department": "Emergency Medicine",
    "title": "Emergency Department Assistant",
    "description": "Assist in the emergency department during busy hours",
    "duration": "6 months",
    "requirements": [
      "Basic life support certification",
      "Medical student year 3+"
    ],
    "location": "Lohm\u00fchlenstra\u00dfe 5, 20099 Hamburg",
    "latitude": 53.5553,
    "longitude": 10.0114,
    "stipend": 800.0,
    "created_at": "2025-04-17T13:48:44.392519",
    "updated_at": "2025-04-17T13:48:44.392521"
  },
  {
    "id": "a93be1a2-2c2b-4824-b8ef-2ff68b3f0eef",
    "name": "Asklepios Klinik Barmbek",
    "department": "Pediatrics",
    "title": "Pediatric Ward Assistant",
    "description": "Support pediatric ward staff in daily activities",
    "duration": "4 months",
    "requirements": [
      "Experience with children",
      "Medical student year 2+"
    ],
    "location": "R\u00fcbenkamp 220, 22307 Hamburg",
    "latitude": 53.5869,
    "longitude": 10.0406,
    "stipend": 700.0,
    "created_at": "2025-04-17T13:48:44.392639",
    "updated_at": "2025-04-17T13:48:44.392640"
  }
]